<annotation>
	<object>
		<bndbox>
			<ymin>400.0</ymin>
			<xmax>639.0</xmax>
			<ymax>430.0</ymax>
			<xmin>615.0</xmin>
		</bndbox>
		<name>person</name>
		<truncated>0</truncated>
		<difficult>0</difficult>
	</object>
	<object>
		<bndbox>
			<ymin>425.0</ymin>
			<xmax>661.0</xmax>
			<ymax>450.0</ymax>
			<xmin>638.0</xmin>
		</bndbox>
		<name>bicycle</name>
		<truncated>0</truncated>
		<difficult>0</difficult>
	</object>
	<object>
		<bndbox>
			<ymin>389.0</ymin>
			<xmax>1316.0</xmax>
			<ymax>500.0</ymax>
			<xmin>1234.0</xmin>
		</bndbox>
		<name>car</name>
		<truncated>0</truncated>
		<difficult>0</difficult>
	</object>
	<object>
		<bndbox>
			<ymin>380.0</ymin>
			<xmax>1411.0</xmax>
			<ymax>520.0</ymax>
			<xmin>1291.0</xmin>
		</bndbox>
		<name>car</name>
		<truncated>0</truncated>
		<difficult>0</difficult>
	</object>
	<object>
		<bndbox>
			<ymin>376.0</ymin>
			<xmax>1554.0</xmax>
			<ymax>552.0</ymax>
			<xmin>1341.0</xmin>
		</bndbox>
		<name>car</name>
		<truncated>0</truncated>
		<difficult>0</difficult>
	</object>
	<object>
		<bndbox>
			<ymin>359.0</ymin>
			<xmax>1797.0</xmax>
			<ymax>614.0</ymax>
			<xmin>1476.0</xmin>
		</bndbox>
		<name>car</name>
		<truncated>0</truncated>
		<difficult>0</difficult>
	</object>
	<object>
		<bndbox>
			<ymin>336.0</ymin>
			<xmax>2042.0</xmax>
			<ymax>733.0</ymax>
			<xmin>1669.0</xmin>
		</bndbox>
		<name>car</name>
		<truncated>0</truncated>
		<difficult>0</difficult>
	</object>
	<object>
		<bndbox>
			<ymin>540.0</ymin>
			<xmax>2042.0</xmax>
			<ymax>737.0</ymax>
			<xmin>1995.0</xmin>
		</bndbox>
		<name>car</name>
		<truncated>0</truncated>
		<difficult>0</difficult>
	</object>
	<object>
		<bndbox>
			<ymin>402.0</ymin>
			<xmax>647.0</xmax>
			<ymax>501.0</ymax>
			<xmin>558.0</xmin>
		</bndbox>
		<name>car</name>
		<truncated>0</truncated>
		<difficult>0</difficult>
	</object>
	<object>
		<bndbox>
			<ymin>380.0</ymin>
			<xmax>936.0</xmax>
			<ymax>485.0</ymax>
			<xmin>809.0</xmin>
		</bndbox>
		<name>car</name>
		<truncated>0</truncated>
		<difficult>0</difficult>
	</object>
	<object>
		<bndbox>
			<ymin>402.0</ymin>
			<xmax>598.0</xmax>
			<ymax>516.0</ymax>
			<xmin>488.0</xmin>
		</bndbox>
		<name>car</name>
		<truncated>0</truncated>
		<difficult>0</difficult>
	</object>
	<object>
		<bndbox>
			<ymin>397.0</ymin>
			<xmax>520.0</xmax>
			<ymax>544.0</ymax>
			<xmin>296.0</xmin>
		</bndbox>
		<name>car</name>
		<truncated>0</truncated>
		<difficult>0</difficult>
	</object>
	<object>
		<bndbox>
			<ymin>413.0</ymin>
			<xmax>187.0</xmax>
			<ymax>624.0</ymax>
			<xmin>6.0</xmin>
		</bndbox>
		<name>car</name>
		<truncated>0</truncated>
		<difficult>0</difficult>
	</object>
	<object>
		<bndbox>
			<ymin>410.0</ymin>
			<xmax>1092.0</xmax>
			<ymax>435.0</ymax>
			<xmin>1062.0</xmin>
		</bndbox>
		<name>bicycle</name>
		<truncated>0</truncated>
		<difficult>0</difficult>
	</object>
	<object>
		<bndbox>
			<ymin>431.0</ymin>
			<xmax>714.0</xmax>
			<ymax>482.0</ymax>
			<xmin>660.0</xmin>
		</bndbox>
		<name>bicycle</name>
		<truncated>0</truncated>
		<difficult>0</difficult>
	</object>
	<object>
		<bndbox>
			<ymin>439.0</ymin>
			<xmax>707.0</xmax>
			<ymax>484.0</ymax>
			<xmin>668.0</xmin>
		</bndbox>
		<name>bicycle</name>
		<truncated>0</truncated>
		<difficult>0</difficult>
	</object>
	<object>
		<bndbox>
			<ymin>440.0</ymin>
			<xmax>700.0</xmax>
			<ymax>484.0</ymax>
			<xmin>661.0</xmin>
		</bndbox>
		<name>bicycle</name>
		<truncated>0</truncated>
		<difficult>0</difficult>
	</object>
	<object>
		<bndbox>
			<ymin>448.0</ymin>
			<xmax>695.0</xmax>
			<ymax>487.0</ymax>
			<xmin>646.0</xmin>
		</bndbox>
		<name>bicycle</name>
		<truncated>0</truncated>
		<difficult>0</difficult>
	</object>
	<object>
		<bndbox>
			<ymin>451.0</ymin>
			<xmax>687.0</xmax>
			<ymax>490.0</ymax>
			<xmin>645.0</xmin>
		</bndbox>
		<name>bicycle</name>
		<truncated>0</truncated>
		<difficult>0</difficult>
	</object>
	<filename>source_strasbourg_000001_015974_leftImg8bit.jpg</filename>
	<folder>VOC2007</folder>
	<size>
		<height>2048</height>
		<width>1024</width>
		<depth>3</depth>
	</size>
	<segmented>0</segmented>
</annotation>
