<annotation>
	<object>
		<bndbox>
			<ymin>434.0</ymin>
			<xmax>1134.0</xmax>
			<ymax>498.0</ymax>
			<xmin>961.0</xmin>
		</bndbox>
		<name>car</name>
		<truncated>0</truncated>
		<difficult>0</difficult>
	</object>
	<object>
		<bndbox>
			<ymin>438.0</ymin>
			<xmax>1063.0</xmax>
			<ymax>485.0</ymax>
			<xmin>1041.0</xmin>
		</bndbox>
		<name>person</name>
		<truncated>0</truncated>
		<difficult>0</difficult>
	</object>
	<object>
		<bndbox>
			<ymin>437.0</ymin>
			<xmax>1040.0</xmax>
			<ymax>487.0</ymax>
			<xmin>1016.0</xmin>
		</bndbox>
		<name>person</name>
		<truncated>0</truncated>
		<difficult>0</difficult>
	</object>
	<object>
		<bndbox>
			<ymin>439.0</ymin>
			<xmax>973.0</xmax>
			<ymax>501.0</ymax>
			<xmin>926.0</xmin>
		</bndbox>
		<name>car</name>
		<truncated>0</truncated>
		<difficult>0</difficult>
	</object>
	<object>
		<bndbox>
			<ymin>427.0</ymin>
			<xmax>949.0</xmax>
			<ymax>521.0</ymax>
			<xmin>841.0</xmin>
		</bndbox>
		<name>car</name>
		<truncated>0</truncated>
		<difficult>0</difficult>
	</object>
	<object>
		<bndbox>
			<ymin>437.0</ymin>
			<xmax>937.0</xmax>
			<ymax>551.0</ymax>
			<xmin>821.0</xmin>
		</bndbox>
		<name>car</name>
		<truncated>0</truncated>
		<difficult>0</difficult>
	</object>
	<object>
		<bndbox>
			<ymin>427.0</ymin>
			<xmax>868.0</xmax>
			<ymax>613.0</ymax>
			<xmin>750.0</xmin>
		</bndbox>
		<name>car</name>
		<truncated>0</truncated>
		<difficult>0</difficult>
	</object>
	<object>
		<bndbox>
			<ymin>417.0</ymin>
			<xmax>821.0</xmax>
			<ymax>661.0</ymax>
			<xmin>629.0</xmin>
		</bndbox>
		<name>car</name>
		<truncated>0</truncated>
		<difficult>0</difficult>
	</object>
	<object>
		<bndbox>
			<ymin>398.0</ymin>
			<xmax>761.0</xmax>
			<ymax>791.0</ymax>
			<xmin>201.0</xmin>
		</bndbox>
		<name>car</name>
		<truncated>0</truncated>
		<difficult>0</difficult>
	</object>
	<object>
		<bndbox>
			<ymin>383.0</ymin>
			<xmax>487.0</xmax>
			<ymax>1018.0</ymax>
			<xmin>6.0</xmin>
		</bndbox>
		<name>car</name>
		<truncated>0</truncated>
		<difficult>0</difficult>
	</object>
	<object>
		<bndbox>
			<ymin>439.0</ymin>
			<xmax>1048.0</xmax>
			<ymax>459.0</ymax>
			<xmin>1035.0</xmin>
		</bndbox>
		<name>car</name>
		<truncated>0</truncated>
		<difficult>0</difficult>
	</object>
	<object>
		<bndbox>
			<ymin>441.0</ymin>
			<xmax>1173.0</xmax>
			<ymax>521.0</ymax>
			<xmin>1112.0</xmin>
		</bndbox>
		<name>car</name>
		<truncated>0</truncated>
		<difficult>0</difficult>
	</object>
	<object>
		<bndbox>
			<ymin>439.0</ymin>
			<xmax>1197.0</xmax>
			<ymax>544.0</ymax>
			<xmin>1148.0</xmin>
		</bndbox>
		<name>car</name>
		<truncated>0</truncated>
		<difficult>0</difficult>
	</object>
	<object>
		<bndbox>
			<ymin>437.0</ymin>
			<xmax>1390.0</xmax>
			<ymax>596.0</ymax>
			<xmin>1217.0</xmin>
		</bndbox>
		<name>car</name>
		<truncated>0</truncated>
		<difficult>0</difficult>
	</object>
	<object>
		<bndbox>
			<ymin>381.0</ymin>
			<xmax>1873.0</xmax>
			<ymax>774.0</ymax>
			<xmin>1323.0</xmin>
		</bndbox>
		<name>car</name>
		<truncated>0</truncated>
		<difficult>0</difficult>
	</object>
	<filename>source_bremen_000214_000019_leftImg8bit.jpg</filename>
	<folder>VOC2007</folder>
	<size>
		<height>2048</height>
		<width>1024</width>
		<depth>3</depth>
	</size>
	<segmented>0</segmented>
</annotation>
