<annotation>
	<object>
		<bndbox>
			<ymin>381.0</ymin>
			<xmax>1299.0</xmax>
			<ymax>410.0</ymax>
			<xmin>1256.0</xmin>
		</bndbox>
		<name>car</name>
		<truncated>0</truncated>
		<difficult>0</difficult>
	</object>
	<object>
		<bndbox>
			<ymin>416.0</ymin>
			<xmax>1113.0</xmax>
			<ymax>438.0</ymax>
			<xmin>1061.0</xmin>
		</bndbox>
		<name>car</name>
		<truncated>0</truncated>
		<difficult>0</difficult>
	</object>
	<object>
		<bndbox>
			<ymin>415.0</ymin>
			<xmax>1153.0</xmax>
			<ymax>458.0</ymax>
			<xmin>1093.0</xmin>
		</bndbox>
		<name>car</name>
		<truncated>0</truncated>
		<difficult>0</difficult>
	</object>
	<object>
		<bndbox>
			<ymin>410.0</ymin>
			<xmax>1098.0</xmax>
			<ymax>462.0</ymax>
			<xmin>1010.0</xmin>
		</bndbox>
		<name>car</name>
		<truncated>0</truncated>
		<difficult>0</difficult>
	</object>
	<object>
		<bndbox>
			<ymin>398.0</ymin>
			<xmax>1019.0</xmax>
			<ymax>460.0</ymax>
			<xmin>963.0</xmin>
		</bndbox>
		<name>car</name>
		<truncated>0</truncated>
		<difficult>0</difficult>
	</object>
	<object>
		<bndbox>
			<ymin>404.0</ymin>
			<xmax>531.0</xmax>
			<ymax>534.0</ymax>
			<xmin>332.0</xmin>
		</bndbox>
		<name>car</name>
		<truncated>0</truncated>
		<difficult>0</difficult>
	</object>
	<object>
		<bndbox>
			<ymin>405.0</ymin>
			<xmax>1216.0</xmax>
			<ymax>469.0</ymax>
			<xmin>1142.0</xmin>
		</bndbox>
		<name>car</name>
		<truncated>0</truncated>
		<difficult>0</difficult>
	</object>
	<object>
		<bndbox>
			<ymin>401.0</ymin>
			<xmax>1316.0</xmax>
			<ymax>491.0</ymax>
			<xmin>1155.0</xmin>
		</bndbox>
		<name>car</name>
		<truncated>0</truncated>
		<difficult>0</difficult>
	</object>
	<filename>source_erfurt_000030_000019_leftImg8bit.jpg</filename>
	<folder>VOC2007</folder>
	<size>
		<height>2048</height>
		<width>1024</width>
		<depth>3</depth>
	</size>
	<segmented>0</segmented>
</annotation>
