<annotation>
	<object>
		<bndbox>
			<ymin>424.0</ymin>
			<xmax>1201.0</xmax>
			<ymax>491.0</ymax>
			<xmin>992.0</xmin>
		</bndbox>
		<name>car</name>
		<truncated>0</truncated>
		<difficult>0</difficult>
	</object>
	<object>
		<bndbox>
			<ymin>406.0</ymin>
			<xmax>541.0</xmax>
			<ymax>498.0</ymax>
			<xmin>442.0</xmin>
		</bndbox>
		<name>bicycle</name>
		<truncated>0</truncated>
		<difficult>0</difficult>
	</object>
	<object>
		<bndbox>
			<ymin>402.0</ymin>
			<xmax>633.0</xmax>
			<ymax>483.0</ymax>
			<xmin>594.0</xmin>
		</bndbox>
		<name>person</name>
		<truncated>0</truncated>
		<difficult>0</difficult>
	</object>
	<object>
		<bndbox>
			<ymin>363.0</ymin>
			<xmax>42.0</xmax>
			<ymax>504.0</ymax>
			<xmin>6.0</xmin>
		</bndbox>
		<name>rider</name>
		<truncated>0</truncated>
		<difficult>0</difficult>
	</object>
	<object>
		<bndbox>
			<ymin>424.0</ymin>
			<xmax>1135.0</xmax>
			<ymax>458.0</ymax>
			<xmin>1101.0</xmin>
		</bndbox>
		<name>car</name>
		<truncated>0</truncated>
		<difficult>0</difficult>
	</object>
	<object>
		<bndbox>
			<ymin>420.0</ymin>
			<xmax>1244.0</xmax>
			<ymax>515.0</ymax>
			<xmin>1161.0</xmin>
		</bndbox>
		<name>car</name>
		<truncated>0</truncated>
		<difficult>0</difficult>
	</object>
	<object>
		<bndbox>
			<ymin>408.0</ymin>
			<xmax>1321.0</xmax>
			<ymax>537.0</ymax>
			<xmin>1197.0</xmin>
		</bndbox>
		<name>car</name>
		<truncated>0</truncated>
		<difficult>0</difficult>
	</object>
	<object>
		<bndbox>
			<ymin>408.0</ymin>
			<xmax>1439.0</xmax>
			<ymax>578.0</ymax>
			<xmin>1261.0</xmin>
		</bndbox>
		<name>car</name>
		<truncated>0</truncated>
		<difficult>0</difficult>
	</object>
	<object>
		<bndbox>
			<ymin>413.0</ymin>
			<xmax>1692.0</xmax>
			<ymax>639.0</ymax>
			<xmin>1336.0</xmin>
		</bndbox>
		<name>car</name>
		<truncated>0</truncated>
		<difficult>0</difficult>
	</object>
	<object>
		<bndbox>
			<ymin>432.0</ymin>
			<xmax>1074.0</xmax>
			<ymax>451.0</ymax>
			<xmin>1039.0</xmin>
		</bndbox>
		<name>car</name>
		<truncated>0</truncated>
		<difficult>0</difficult>
	</object>
	<object>
		<bndbox>
			<ymin>418.0</ymin>
			<xmax>982.0</xmax>
			<ymax>463.0</ymax>
			<xmin>944.0</xmin>
		</bndbox>
		<name>car</name>
		<truncated>0</truncated>
		<difficult>0</difficult>
	</object>
	<object>
		<bndbox>
			<ymin>421.0</ymin>
			<xmax>953.0</xmax>
			<ymax>470.0</ymax>
			<xmin>907.0</xmin>
		</bndbox>
		<name>car</name>
		<truncated>0</truncated>
		<difficult>0</difficult>
	</object>
	<object>
		<bndbox>
			<ymin>420.0</ymin>
			<xmax>914.0</xmax>
			<ymax>484.0</ymax>
			<xmin>889.0</xmin>
		</bndbox>
		<name>car</name>
		<truncated>0</truncated>
		<difficult>0</difficult>
	</object>
	<object>
		<bndbox>
			<ymin>409.0</ymin>
			<xmax>883.0</xmax>
			<ymax>505.0</ymax>
			<xmin>820.0</xmin>
		</bndbox>
		<name>car</name>
		<truncated>0</truncated>
		<difficult>0</difficult>
	</object>
	<object>
		<bndbox>
			<ymin>404.0</ymin>
			<xmax>830.0</xmax>
			<ymax>525.0</ymax>
			<xmin>666.0</xmin>
		</bndbox>
		<name>car</name>
		<truncated>0</truncated>
		<difficult>0</difficult>
	</object>
	<object>
		<bndbox>
			<ymin>428.0</ymin>
			<xmax>2042.0</xmax>
			<ymax>551.0</ymax>
			<xmin>2000.0</xmin>
		</bndbox>
		<name>bicycle</name>
		<truncated>0</truncated>
		<difficult>0</difficult>
	</object>
	<object>
		<bndbox>
			<ymin>501.0</ymin>
			<xmax>56.0</xmax>
			<ymax>682.0</ymax>
			<xmin>6.0</xmin>
		</bndbox>
		<name>bicycle</name>
		<truncated>0</truncated>
		<difficult>0</difficult>
	</object>
	<object>
		<bndbox>
			<ymin>425.0</ymin>
			<xmax>602.0</xmax>
			<ymax>488.0</ymax>
			<xmin>547.0</xmin>
		</bndbox>
		<name>bicycle</name>
		<truncated>0</truncated>
		<difficult>0</difficult>
	</object>
	<filename>source_bremen_000212_000019_leftImg8bit.jpg</filename>
	<folder>VOC2007</folder>
	<size>
		<height>2048</height>
		<width>1024</width>
		<depth>3</depth>
	</size>
	<segmented>0</segmented>
</annotation>
