<annotation>
	<object>
		<bndbox>
			<ymin>360.0</ymin>
			<xmax>1268.0</xmax>
			<ymax>412.0</ymax>
			<xmin>1140.0</xmin>
		</bndbox>
		<name>car</name>
		<truncated>0</truncated>
		<difficult>0</difficult>
	</object>
	<object>
		<bndbox>
			<ymin>516.0</ymin>
			<xmax>1923.0</xmax>
			<ymax>531.0</ymax>
			<xmin>1879.0</xmin>
		</bndbox>
		<name>person</name>
		<truncated>0</truncated>
		<difficult>0</difficult>
	</object>
	<object>
		<bndbox>
			<ymin>349.0</ymin>
			<xmax>1725.0</xmax>
			<ymax>514.0</ymax>
			<xmin>1661.0</xmin>
		</bndbox>
		<name>person</name>
		<truncated>0</truncated>
		<difficult>0</difficult>
	</object>
	<object>
		<bndbox>
			<ymin>342.0</ymin>
			<xmax>1801.0</xmax>
			<ymax>493.0</ymax>
			<xmin>1745.0</xmin>
		</bndbox>
		<name>person</name>
		<truncated>0</truncated>
		<difficult>0</difficult>
	</object>
	<object>
		<bndbox>
			<ymin>376.0</ymin>
			<xmax>1837.0</xmax>
			<ymax>529.0</ymax>
			<xmin>1748.0</xmin>
		</bndbox>
		<name>person</name>
		<truncated>0</truncated>
		<difficult>0</difficult>
	</object>
	<object>
		<bndbox>
			<ymin>408.0</ymin>
			<xmax>1118.0</xmax>
			<ymax>438.0</ymax>
			<xmin>1101.0</xmin>
		</bndbox>
		<name>person</name>
		<truncated>0</truncated>
		<difficult>0</difficult>
	</object>
	<object>
		<bndbox>
			<ymin>403.0</ymin>
			<xmax>1002.0</xmax>
			<ymax>428.0</ymax>
			<xmin>988.0</xmin>
		</bndbox>
		<name>person</name>
		<truncated>0</truncated>
		<difficult>0</difficult>
	</object>
	<object>
		<bndbox>
			<ymin>406.0</ymin>
			<xmax>430.0</xmax>
			<ymax>506.0</ymax>
			<xmin>381.0</xmin>
		</bndbox>
		<name>person</name>
		<truncated>0</truncated>
		<difficult>0</difficult>
	</object>
	<object>
		<bndbox>
			<ymin>365.0</ymin>
			<xmax>1540.0</xmax>
			<ymax>490.0</ymax>
			<xmin>1478.0</xmin>
		</bndbox>
		<name>rider</name>
		<truncated>0</truncated>
		<difficult>0</difficult>
	</object>
	<object>
		<bndbox>
			<ymin>369.0</ymin>
			<xmax>1229.0</xmax>
			<ymax>378.0</ymax>
			<xmin>1216.0</xmin>
		</bndbox>
		<name>car</name>
		<truncated>0</truncated>
		<difficult>0</difficult>
	</object>
	<object>
		<bndbox>
			<ymin>391.0</ymin>
			<xmax>1192.0</xmax>
			<ymax>400.0</ymax>
			<xmin>1169.0</xmin>
		</bndbox>
		<name>car</name>
		<truncated>0</truncated>
		<difficult>0</difficult>
	</object>
	<object>
		<bndbox>
			<ymin>398.0</ymin>
			<xmax>1206.0</xmax>
			<ymax>437.0</ymax>
			<xmin>1167.0</xmin>
		</bndbox>
		<name>car</name>
		<truncated>0</truncated>
		<difficult>0</difficult>
	</object>
	<object>
		<bndbox>
			<ymin>406.0</ymin>
			<xmax>1088.0</xmax>
			<ymax>442.0</ymax>
			<xmin>1051.0</xmin>
		</bndbox>
		<name>car</name>
		<truncated>0</truncated>
		<difficult>0</difficult>
	</object>
	<object>
		<bndbox>
			<ymin>410.0</ymin>
			<xmax>1072.0</xmax>
			<ymax>444.0</ymax>
			<xmin>1048.0</xmin>
		</bndbox>
		<name>car</name>
		<truncated>0</truncated>
		<difficult>0</difficult>
	</object>
	<object>
		<bndbox>
			<ymin>408.0</ymin>
			<xmax>1063.0</xmax>
			<ymax>445.0</ymax>
			<xmin>1018.0</xmin>
		</bndbox>
		<name>car</name>
		<truncated>0</truncated>
		<difficult>0</difficult>
	</object>
	<object>
		<bndbox>
			<ymin>411.0</ymin>
			<xmax>1048.0</xmax>
			<ymax>454.0</ymax>
			<xmin>989.0</xmin>
		</bndbox>
		<name>car</name>
		<truncated>0</truncated>
		<difficult>0</difficult>
	</object>
	<object>
		<bndbox>
			<ymin>407.0</ymin>
			<xmax>991.0</xmax>
			<ymax>464.0</ymax>
			<xmin>941.0</xmin>
		</bndbox>
		<name>car</name>
		<truncated>0</truncated>
		<difficult>0</difficult>
	</object>
	<object>
		<bndbox>
			<ymin>398.0</ymin>
			<xmax>949.0</xmax>
			<ymax>475.0</ymax>
			<xmin>866.0</xmin>
		</bndbox>
		<name>car</name>
		<truncated>0</truncated>
		<difficult>0</difficult>
	</object>
	<object>
		<bndbox>
			<ymin>408.0</ymin>
			<xmax>918.0</xmax>
			<ymax>479.0</ymax>
			<xmin>831.0</xmin>
		</bndbox>
		<name>car</name>
		<truncated>0</truncated>
		<difficult>0</difficult>
	</object>
	<object>
		<bndbox>
			<ymin>306.0</ymin>
			<xmax>1453.0</xmax>
			<ymax>508.0</ymax>
			<xmin>1273.0</xmin>
		</bndbox>
		<name>truck</name>
		<truncated>0</truncated>
		<difficult>0</difficult>
	</object>
	<object>
		<bndbox>
			<ymin>368.0</ymin>
			<xmax>2042.0</xmax>
			<ymax>549.0</ymax>
			<xmin>1911.0</xmin>
		</bndbox>
		<name>motorcycle</name>
		<truncated>0</truncated>
		<difficult>0</difficult>
	</object>
	<object>
		<bndbox>
			<ymin>427.0</ymin>
			<xmax>867.0</xmax>
			<ymax>488.0</ymax>
			<xmin>805.0</xmin>
		</bndbox>
		<name>motorcycle</name>
		<truncated>0</truncated>
		<difficult>0</difficult>
	</object>
	<object>
		<bndbox>
			<ymin>437.0</ymin>
			<xmax>1554.0</xmax>
			<ymax>519.0</ymax>
			<xmin>1459.0</xmin>
		</bndbox>
		<name>bicycle</name>
		<truncated>0</truncated>
		<difficult>0</difficult>
	</object>
	<filename>source_stuttgart_000072_000019_leftImg8bit.jpg</filename>
	<folder>VOC2007</folder>
	<size>
		<height>2048</height>
		<width>1024</width>
		<depth>3</depth>
	</size>
	<segmented>0</segmented>
</annotation>
