<annotation>
	<object>
		<bndbox>
			<ymin>484.0</ymin>
			<xmax>2007.0</xmax>
			<ymax>518.0</ymax>
			<xmin>1889.0</xmin>
		</bndbox>
		<name>bicycle</name>
		<truncated>0</truncated>
		<difficult>0</difficult>
	</object>
	<object>
		<bndbox>
			<ymin>480.0</ymin>
			<xmax>301.0</xmax>
			<ymax>499.0</ymax>
			<xmin>285.0</xmin>
		</bndbox>
		<name>person</name>
		<truncated>0</truncated>
		<difficult>0</difficult>
	</object>
	<object>
		<bndbox>
			<ymin>474.0</ymin>
			<xmax>324.0</xmax>
			<ymax>498.0</ymax>
			<xmin>300.0</xmin>
		</bndbox>
		<name>person</name>
		<truncated>0</truncated>
		<difficult>0</difficult>
	</object>
	<object>
		<bndbox>
			<ymin>503.0</ymin>
			<xmax>558.0</xmax>
			<ymax>517.0</ymax>
			<xmin>536.0</xmin>
		</bndbox>
		<name>person</name>
		<truncated>0</truncated>
		<difficult>0</difficult>
	</object>
	<object>
		<bndbox>
			<ymin>425.0</ymin>
			<xmax>300.0</xmax>
			<ymax>576.0</ymax>
			<xmin>214.0</xmin>
		</bndbox>
		<name>person</name>
		<truncated>0</truncated>
		<difficult>0</difficult>
	</object>
	<object>
		<bndbox>
			<ymin>435.0</ymin>
			<xmax>496.0</xmax>
			<ymax>587.0</ymax>
			<xmin>414.0</xmin>
		</bndbox>
		<name>person</name>
		<truncated>0</truncated>
		<difficult>0</difficult>
	</object>
	<object>
		<bndbox>
			<ymin>458.0</ymin>
			<xmax>1010.0</xmax>
			<ymax>540.0</ymax>
			<xmin>980.0</xmin>
		</bndbox>
		<name>person</name>
		<truncated>0</truncated>
		<difficult>0</difficult>
	</object>
	<object>
		<bndbox>
			<ymin>428.0</ymin>
			<xmax>980.0</xmax>
			<ymax>575.0</ymax>
			<xmin>934.0</xmin>
		</bndbox>
		<name>person</name>
		<truncated>0</truncated>
		<difficult>0</difficult>
	</object>
	<object>
		<bndbox>
			<ymin>460.0</ymin>
			<xmax>1325.0</xmax>
			<ymax>515.0</ymax>
			<xmin>1295.0</xmin>
		</bndbox>
		<name>person</name>
		<truncated>0</truncated>
		<difficult>0</difficult>
	</object>
	<object>
		<bndbox>
			<ymin>440.0</ymin>
			<xmax>1389.0</xmax>
			<ymax>578.0</ymax>
			<xmin>1340.0</xmin>
		</bndbox>
		<name>person</name>
		<truncated>0</truncated>
		<difficult>0</difficult>
	</object>
	<object>
		<bndbox>
			<ymin>467.0</ymin>
			<xmax>1693.0</xmax>
			<ymax>480.0</ymax>
			<xmin>1680.0</xmin>
		</bndbox>
		<name>person</name>
		<truncated>0</truncated>
		<difficult>0</difficult>
	</object>
	<object>
		<bndbox>
			<ymin>464.0</ymin>
			<xmax>1709.0</xmax>
			<ymax>493.0</ymax>
			<xmin>1693.0</xmin>
		</bndbox>
		<name>person</name>
		<truncated>0</truncated>
		<difficult>0</difficult>
	</object>
	<object>
		<bndbox>
			<ymin>488.0</ymin>
			<xmax>1733.0</xmax>
			<ymax>544.0</ymax>
			<xmin>1698.0</xmin>
		</bndbox>
		<name>person</name>
		<truncated>0</truncated>
		<difficult>0</difficult>
	</object>
	<object>
		<bndbox>
			<ymin>463.0</ymin>
			<xmax>1867.0</xmax>
			<ymax>519.0</ymax>
			<xmin>1848.0</xmin>
		</bndbox>
		<name>person</name>
		<truncated>0</truncated>
		<difficult>0</difficult>
	</object>
	<object>
		<bndbox>
			<ymin>468.0</ymin>
			<xmax>1939.0</xmax>
			<ymax>497.0</ymax>
			<xmin>1917.0</xmin>
		</bndbox>
		<name>person</name>
		<truncated>0</truncated>
		<difficult>0</difficult>
	</object>
	<object>
		<bndbox>
			<ymin>454.0</ymin>
			<xmax>1894.0</xmax>
			<ymax>537.0</ymax>
			<xmin>1861.0</xmin>
		</bndbox>
		<name>person</name>
		<truncated>0</truncated>
		<difficult>0</difficult>
	</object>
	<object>
		<bndbox>
			<ymin>458.0</ymin>
			<xmax>1852.0</xmax>
			<ymax>531.0</ymax>
			<xmin>1825.0</xmin>
		</bndbox>
		<name>person</name>
		<truncated>0</truncated>
		<difficult>0</difficult>
	</object>
	<object>
		<bndbox>
			<ymin>451.0</ymin>
			<xmax>1793.0</xmax>
			<ymax>553.0</ymax>
			<xmin>1750.0</xmin>
		</bndbox>
		<name>person</name>
		<truncated>0</truncated>
		<difficult>0</difficult>
	</object>
	<object>
		<bndbox>
			<ymin>447.0</ymin>
			<xmax>1847.0</xmax>
			<ymax>555.0</ymax>
			<xmin>1795.0</xmin>
		</bndbox>
		<name>person</name>
		<truncated>0</truncated>
		<difficult>0</difficult>
	</object>
	<object>
		<bndbox>
			<ymin>376.0</ymin>
			<xmax>1256.0</xmax>
			<ymax>615.0</ymax>
			<xmin>1155.0</xmin>
		</bndbox>
		<name>rider</name>
		<truncated>0</truncated>
		<difficult>0</difficult>
	</object>
	<object>
		<bndbox>
			<ymin>476.0</ymin>
			<xmax>234.0</xmax>
			<ymax>529.0</ymax>
			<xmin>6.0</xmin>
		</bndbox>
		<name>car</name>
		<truncated>0</truncated>
		<difficult>0</difficult>
	</object>
	<object>
		<bndbox>
			<ymin>454.0</ymin>
			<xmax>865.0</xmax>
			<ymax>570.0</ymax>
			<xmin>702.0</xmin>
		</bndbox>
		<name>car</name>
		<truncated>0</truncated>
		<difficult>0</difficult>
	</object>
	<object>
		<bndbox>
			<ymin>467.0</ymin>
			<xmax>1710.0</xmax>
			<ymax>547.0</ymax>
			<xmin>1436.0</xmin>
		</bndbox>
		<name>car</name>
		<truncated>0</truncated>
		<difficult>0</difficult>
	</object>
	<object>
		<bndbox>
			<ymin>469.0</ymin>
			<xmax>1241.0</xmax>
			<ymax>635.0</ymax>
			<xmin>1173.0</xmin>
		</bndbox>
		<name>bicycle</name>
		<truncated>0</truncated>
		<difficult>0</difficult>
	</object>
	<object>
		<bndbox>
			<ymin>483.0</ymin>
			<xmax>1866.0</xmax>
			<ymax>553.0</ymax>
			<xmin>1772.0</xmin>
		</bndbox>
		<name>bicycle</name>
		<truncated>0</truncated>
		<difficult>0</difficult>
	</object>
	<filename>source_jena_000089_000019_leftImg8bit.jpg</filename>
	<folder>VOC2007</folder>
	<size>
		<height>2048</height>
		<width>1024</width>
		<depth>3</depth>
	</size>
	<segmented>0</segmented>
</annotation>
