<annotation>
	<folder>Unspecified</folder>
	<filename>munster_000059_000019_leftImg8bit.jpg</filename>
	<segmented>0</segmented>
	<size>
		<width>2048</width>
		<height>1024</height>
		<depth>3</depth>
	</size>
	<object>
		<bndbox>
			<xmin>308</xmin>
			<ymin>402</ymin>
			<xmax>327</xmax>
			<ymax>422</ymax>
		</bndbox>
		<name>person</name>
		<difficult>0</difficult>
		<truncated>0</truncated>
		<occluded>0</occluded>
		<pose>Unspecified</pose>
	</object>
	<object>
		<bndbox>
			<xmin>328</xmin>
			<ymin>403</ymin>
			<xmax>342</xmax>
			<ymax>426</ymax>
		</bndbox>
		<name>person</name>
		<difficult>0</difficult>
		<truncated>0</truncated>
		<occluded>0</occluded>
		<pose>Unspecified</pose>
	</object>
	<object>
		<bndbox>
			<xmin>382</xmin>
			<ymin>403</ymin>
			<xmax>399</xmax>
			<ymax>444</ymax>
		</bndbox>
		<name>person</name>
		<difficult>0</difficult>
		<truncated>0</truncated>
		<occluded>0</occluded>
		<pose>Unspecified</pose>
	</object>
	<object>
		<bndbox>
			<xmin>365</xmin>
			<ymin>403</ymin>
			<xmax>382</xmax>
			<ymax>456</ymax>
		</bndbox>
		<name>person</name>
		<difficult>0</difficult>
		<truncated>0</truncated>
		<occluded>0</occluded>
		<pose>Unspecified</pose>
	</object>
	<object>
		<bndbox>
			<xmin>565</xmin>
			<ymin>398</ymin>
			<xmax>583</xmax>
			<ymax>452</ymax>
		</bndbox>
		<name>person</name>
		<difficult>0</difficult>
		<truncated>0</truncated>
		<occluded>0</occluded>
		<pose>Unspecified</pose>
	</object>
	<object>
		<bndbox>
			<xmin>626</xmin>
			<ymin>393</ymin>
			<xmax>641</xmax>
			<ymax>452</ymax>
		</bndbox>
		<name>person</name>
		<difficult>0</difficult>
		<truncated>0</truncated>
		<occluded>0</occluded>
		<pose>Unspecified</pose>
	</object>
	<object>
		<bndbox>
			<xmin>614</xmin>
			<ymin>397</ymin>
			<xmax>639</xmax>
			<ymax>456</ymax>
		</bndbox>
		<name>person</name>
		<difficult>0</difficult>
		<truncated>0</truncated>
		<occluded>0</occluded>
		<pose>Unspecified</pose>
	</object>
	<object>
		<bndbox>
			<xmin>653</xmin>
			<ymin>399</ymin>
			<xmax>672</xmax>
			<ymax>448</ymax>
		</bndbox>
		<name>person</name>
		<difficult>0</difficult>
		<truncated>0</truncated>
		<occluded>0</occluded>
		<pose>Unspecified</pose>
	</object>
	<object>
		<bndbox>
			<xmin>643</xmin>
			<ymin>400</ymin>
			<xmax>660</xmax>
			<ymax>450</ymax>
		</bndbox>
		<name>person</name>
		<difficult>0</difficult>
		<truncated>0</truncated>
		<occluded>0</occluded>
		<pose>Unspecified</pose>
	</object>
	<object>
		<bndbox>
			<xmin>1059</xmin>
			<ymin>395</ymin>
			<xmax>1092</xmax>
			<ymax>446</ymax>
		</bndbox>
		<name>person</name>
		<difficult>0</difficult>
		<truncated>0</truncated>
		<occluded>0</occluded>
		<pose>Unspecified</pose>
	</object>
	<object>
		<bndbox>
			<xmin>1618</xmin>
			<ymin>363</ymin>
			<xmax>1644</xmax>
			<ymax>405</ymax>
		</bndbox>
		<name>person</name>
		<difficult>0</difficult>
		<truncated>0</truncated>
		<occluded>0</occluded>
		<pose>Unspecified</pose>
	</object>
	<object>
		<bndbox>
			<xmin>1353</xmin>
			<ymin>367</ymin>
			<xmax>1378</xmax>
			<ymax>389</ymax>
		</bndbox>
		<name>person</name>
		<difficult>0</difficult>
		<truncated>0</truncated>
		<occluded>0</occluded>
		<pose>Unspecified</pose>
	</object>
	<object>
		<bndbox>
			<xmin>1764</xmin>
			<ymin>383</ymin>
			<xmax>1843</xmax>
			<ymax>409</ymax>
		</bndbox>
		<name>motorcycle</name>
		<difficult>0</difficult>
		<truncated>0</truncated>
		<occluded>0</occluded>
		<pose>Unspecified</pose>
	</object>
	<object>
		<bndbox>
			<xmin>717</xmin>
			<ymin>395</ymin>
			<xmax>830</xmax>
			<ymax>450</ymax>
		</bndbox>
		<name>car</name>
		<difficult>0</difficult>
		<truncated>0</truncated>
		<occluded>0</occluded>
		<pose>Unspecified</pose>
	</object>
	<object>
		<bndbox>
			<xmin>733</xmin>
			<ymin>390</ymin>
			<xmax>753</xmax>
			<ymax>454</ymax>
		</bndbox>
		<name>person</name>
		<difficult>0</difficult>
		<truncated>0</truncated>
		<occluded>0</occluded>
		<pose>Unspecified</pose>
	</object>
	<object>
		<bndbox>
			<xmin>761</xmin>
			<ymin>389</ymin>
			<xmax>778</xmax>
			<ymax>452</ymax>
		</bndbox>
		<name>person</name>
		<difficult>0</difficult>
		<truncated>0</truncated>
		<occluded>0</occluded>
		<pose>Unspecified</pose>
	</object>
	<object>
		<bndbox>
			<xmin>799</xmin>
			<ymin>391</ymin>
			<xmax>851</xmax>
			<ymax>457</ymax>
		</bndbox>
		<name>car</name>
		<difficult>0</difficult>
		<truncated>0</truncated>
		<occluded>0</occluded>
		<pose>Unspecified</pose>
	</object>
	<object>
		<bndbox>
			<xmin>816</xmin>
			<ymin>396</ymin>
			<xmax>854</xmax>
			<ymax>459</ymax>
		</bndbox>
		<name>car</name>
		<difficult>0</difficult>
		<truncated>0</truncated>
		<occluded>0</occluded>
		<pose>Unspecified</pose>
	</object>
	<object>
		<bndbox>
			<xmin>838</xmin>
			<ymin>381</ymin>
			<xmax>924</xmax>
			<ymax>465</ymax>
		</bndbox>
		<name>car</name>
		<difficult>0</difficult>
		<truncated>0</truncated>
		<occluded>0</occluded>
		<pose>Unspecified</pose>
	</object>
	<object>
		<bndbox>
			<xmin>865</xmin>
			<ymin>383</ymin>
			<xmax>942</xmax>
			<ymax>471</ymax>
		</bndbox>
		<name>car</name>
		<difficult>0</difficult>
		<truncated>0</truncated>
		<occluded>0</occluded>
		<pose>Unspecified</pose>
	</object>
	<object>
		<bndbox>
			<xmin>897</xmin>
			<ymin>380</ymin>
			<xmax>1042</xmax>
			<ymax>485</ymax>
		</bndbox>
		<name>car</name>
		<difficult>0</difficult>
		<truncated>0</truncated>
		<occluded>0</occluded>
		<pose>Unspecified</pose>
	</object>
	<object>
		<bndbox>
			<xmin>1180</xmin>
			<ymin>386</ymin>
			<xmax>1233</xmax>
			<ymax>461</ymax>
		</bndbox>
		<name>motorcycle</name>
		<difficult>0</difficult>
		<truncated>0</truncated>
		<occluded>0</occluded>
		<pose>Unspecified</pose>
	</object>
	<object>
		<bndbox>
			<xmin>1310</xmin>
			<ymin>382</ymin>
			<xmax>1391</xmax>
			<ymax>463</ymax>
		</bndbox>
		<name>motorcycle</name>
		<difficult>0</difficult>
		<truncated>0</truncated>
		<occluded>0</occluded>
		<pose>Unspecified</pose>
	</object>
	<object>
		<bndbox>
			<xmin>1088</xmin>
			<ymin>389</ymin>
			<xmax>1121</xmax>
			<ymax>455</ymax>
		</bndbox>
		<name>motorcycle</name>
		<difficult>0</difficult>
		<truncated>0</truncated>
		<occluded>0</occluded>
		<pose>Unspecified</pose>
	</object>
	<object>
		<bndbox>
			<xmin>1131</xmin>
			<ymin>391</ymin>
			<xmax>1180</xmax>
			<ymax>463</ymax>
		</bndbox>
		<name>motorcycle</name>
		<difficult>0</difficult>
		<truncated>0</truncated>
		<occluded>0</occluded>
		<pose>Unspecified</pose>
	</object>
	<object>
		<bndbox>
			<xmin>409</xmin>
			<ymin>329</ymin>
			<xmax>498</xmax>
			<ymax>552</ymax>
		</bndbox>
		<name>rider</name>
		<difficult>0</difficult>
		<truncated>0</truncated>
		<occluded>0</occluded>
		<pose>Unspecified</pose>
	</object>
	<object>
		<bndbox>
			<xmin>415</xmin>
			<ymin>417</ymin>
			<xmax>481</xmax>
			<ymax>593</ymax>
		</bndbox>
		<name>bicycle</name>
		<difficult>0</difficult>
		<truncated>0</truncated>
		<occluded>0</occluded>
		<pose>Unspecified</pose>
	</object>
</annotation>
