<annotation>
	<folder>Unspecified</folder>
	<filename>86.png</filename>
	<segmented>0</segmented>
	<size>
		<width>224</width>
		<height>224</height>
		<depth>3</depth>
	</size>
	<object>
		<bndbox>
			<xmin>60</xmin>
			<ymin>16</ymin>
			<xmax>131</xmax>
			<ymax>77</ymax>
		</bndbox>
		<name>triangle</name>
		<difficult>0</difficult>
		<truncated>0</truncated>
		<occluded>0</occluded>
		<pose>Unspecified</pose>
	</object>
	<object>
		<bndbox>
			<xmin>6</xmin>
			<ymin>24</ymin>
			<xmax>30</xmax>
			<ymax>48</ymax>
		</bndbox>
		<name>circle</name>
		<difficult>0</difficult>
		<truncated>0</truncated>
		<occluded>0</occluded>
		<pose>Unspecified</pose>
	</object>
	<object>
		<bndbox>
			<xmin>165</xmin>
			<ymin>53</ymin>
			<xmax>199</xmax>
			<ymax>82</ymax>
		</bndbox>
		<name>triangle</name>
		<difficult>0</difficult>
		<truncated>0</truncated>
		<occluded>0</occluded>
		<pose>Unspecified</pose>
	</object>
	<object>
		<bndbox>
			<xmin>90</xmin>
			<ymin>145</ymin>
			<xmax>135</xmax>
			<ymax>183</ymax>
		</bndbox>
		<name>triangle</name>
		<difficult>0</difficult>
		<truncated>0</truncated>
		<occluded>0</occluded>
		<pose>Unspecified</pose>
	</object>
	<object>
		<bndbox>
			<xmin>190</xmin>
			<ymin>109</ymin>
			<xmax>214</xmax>
			<ymax>133</ymax>
		</bndbox>
		<name>circle</name>
		<difficult>0</difficult>
		<truncated>0</truncated>
		<occluded>0</occluded>
		<pose>Unspecified</pose>
	</object>
	<object>
		<bndbox>
			<xmin>93</xmin>
			<ymin>101</ymin>
			<xmax>122</xmax>
			<ymax>125</ymax>
		</bndbox>
		<name>triangle</name>
		<difficult>0</difficult>
		<truncated>0</truncated>
		<occluded>0</occluded>
		<pose>Unspecified</pose>
	</object>
</annotation>
